ragit/__init__.py
ragit/main.py
ragit-0.8.dist-info/LICENSE
ragit-0.8.dist-info/METADATA
ragit-0.8.dist-info/WHEEL
ragit-0.8.dist-info/top_level.txt
ragit-0.8.dist-info/RECORD
