Metadata-Version: 2.2
Name: ragit
Version: 0.8
Home-page: https://github.com/stsfaroz/ragit
Author: Salman Faroz
License: MIT
License-File: LICENSE
Requires-Dist: sentence-transformers>=3.4.1
Requires-Dist: pandas>=2.2.3
Requires-Dist: chromadb>=0.6.3
Requires-Dist: setuptools>=75.8.0
Requires-Dist: wheel>=0.45.1
Requires-Dist: twine>=6.1.0
Dynamic: author
Dynamic: description
Dynamic: description-content-type
Dynamic: home-page
Dynamic: license
Dynamic: requires-dist
